gogoanime/__init__.py
gogoanime/downloaders.py
gogoanime/main.py
gogoanime/utils.py
gogoanime_dl-1.2.dist-info/LICENSE
gogoanime_dl-1.2.dist-info/METADATA
gogoanime_dl-1.2.dist-info/WHEEL
gogoanime_dl-1.2.dist-info/top_level.txt
gogoanime_dl-1.2.dist-info/RECORD
