Metadata-Version: 2.1
Name: gogoanime-dl
Version: 1.2
Summary: GoGoAnime file downloader
Home-page: https://github.com/AuraMoon55/
Author: AuraMoon55
Author-email: garganshul553@gmail.com
License: MIT
Classifier: License :: OSI Approved :: MIT License
Classifier: Operating System :: OS Independent
Classifier: Programming Language :: Python
Classifier: Programming Language :: Python :: 3
Classifier: Programming Language :: Python :: 3.6
Classifier: Programming Language :: Python :: 3.7
Classifier: Programming Language :: Python :: 3.8
Classifier: Programming Language :: Python :: 3.9
Classifier: Programming Language :: Python :: 3.10
Classifier: Programming Language :: Python :: Implementation
Classifier: Programming Language :: Python :: Implementation :: CPython
Classifier: Programming Language :: Python :: Implementation :: PyPy
Classifier: Topic :: Internet
Classifier: Topic :: Software Development :: Libraries
Classifier: Topic :: Software Development :: Libraries :: Python Modules
Requires-Python: ~=3.7
License-File: LICENSE
Requires-Dist: requests (==2.23.0)
Requires-Dist: bs4
Requires-Dist: selenium (==4.3.0)
